jamsfetch/__init__.py
jamsfetch/auto.py
jamsfetch/utils/__init__.py
jamsfetch/utils/deconvolute.py
jamsfetch/utils/fetch_alphafold.py
jamsfetch/utils/fetch_assembly.py
jamsfetch/utils/fetch_esm.py
jamsfetch/utils/fetch_nucleotide.py
jamsfetch/utils/fetch_pdb.py
jamsfetch/utils/fetch_uniprot.py
jamsfetch-1.0.3.dist-info/licenses/LICENSE
jamsfetch-1.0.3.dist-info/METADATA
jamsfetch-1.0.3.dist-info/WHEEL
jamsfetch-1.0.3.dist-info/top_level.txt
jamsfetch-1.0.3.dist-info/RECORD
