Metadata-Version: 2.4
Name: jamsfetch
Version: 1.0.3
Summary: JAMS-Fetch (Joint Automated Multi-source Sequence Fetcher) is a Python package. It automates the retrieval of sequence and structure data from major bioinformatics databases using a unified, user-friendly interface.
Author: Anna Szymik, Michal Stanowski, Stanislaw Golebiewski, Joanna Dabrowska
License: MIT
Project-URL: Homepage, https://github.com/aszymik/JAMS
Requires-Python: >=3.6
License-File: LICENSE
Requires-Dist: requests>=2.25
Provides-Extra: test
Requires-Dist: pytest; extra == "test"
Dynamic: license-file
